matchclot/__init__.py
matchclot/py.typed
matchclot/embedding/__init__.py
matchclot/embedding/catalyst_tools.py
matchclot/embedding/models.py
matchclot/embedding/train.py
matchclot/matching/__init__.py
matchclot/matching/matching.py
matchclot/preprocessing/__init__.py
matchclot/preprocessing/preprocess.py
matchclot/run/__init__.py
matchclot/run/evaluate.py
matchclot/run/run.py
matchclot/utils/__init__.py
matchclot/utils/dataloaders.py
matchclot/utils/download.py
matchclot/utils/hyperparameters.py
matchclot-0.1.1.dev1.dist-info/LICENSE
matchclot-0.1.1.dev1.dist-info/METADATA
matchclot-0.1.1.dev1.dist-info/WHEEL
matchclot-0.1.1.dev1.dist-info/entry_points.txt
matchclot-0.1.1.dev1.dist-info/top_level.txt
matchclot-0.1.1.dev1.dist-info/RECORD
