Metadata-Version: 2.1
Name: matchclot
Version: 0.1.1.dev1
Summary: Installable matchclot package.
Home-page: https://github.com/AI4SCR/MatchCLOT
Author: Federico Gossi
Author-email: fgossi@ethz.ch
License-File: LICENSE
Requires-Dist: anndata (>=0.8.0)
Requires-Dist: numpy (>=1.23.4)
Requires-Dist: pandas (>=1.5.1)
Requires-Dist: torch (>=1.13.0)
Requires-Dist: catalyst (>=22.4)
Requires-Dist: harmony-pytorch (>=0.1.7)
Requires-Dist: scikit-learn (>=1.1.3)
Requires-Dist: scipy (>=1.9.3)
Requires-Dist: POT (>=0.8.2)
Requires-Dist: networkx (>=2.8.8)
Requires-Dist: scanpy (>=1.9.1)
Provides-Extra: dev
Requires-Dist: pytest ; extra == 'dev'
Requires-Dist: pytest-cov ; extra == 'dev'
Requires-Dist: black (==22.3.0) ; extra == 'dev'
Requires-Dist: flake8 ; extra == 'dev'
Requires-Dist: mypy ; extra == 'dev'
Requires-Dist: sphinx ; extra == 'dev'
Requires-Dist: sphinx-autodoc-typehints ; extra == 'dev'
Requires-Dist: better-apidoc ; extra == 'dev'
Requires-Dist: six ; extra == 'dev'
Requires-Dist: sphinx-rtd-theme ; extra == 'dev'
Requires-Dist: myst-parser ; extra == 'dev'
Provides-Extra: test
Requires-Dist: pytest ; extra == 'test'
Requires-Dist: pytest-cov ; extra == 'test'
Provides-Extra: vcs
